prestapyt/__init__.py
prestapyt/dict2xml.py
prestapyt/prestapyt.py
prestapyt/version.py
prestapyt/xml2dict.py
prestapyt_flachica-0.11.5.dist-info/LICENSE
prestapyt_flachica-0.11.5.dist-info/METADATA
prestapyt_flachica-0.11.5.dist-info/WHEEL
prestapyt_flachica-0.11.5.dist-info/top_level.txt
prestapyt_flachica-0.11.5.dist-info/RECORD
