Metadata-Version: 2.1
Name: prestapyt-flachica
Version: 0.11.5
Summary: A library to access Prestashop Web Service from Python.
Home-page: http://github.com/prestapyt/prestapyt
Author: Guewen Baconnier
Author-email: guewen.baconnier@gmail.com
License: GNU AGPL-3
Keywords: prestashop api client rest
Classifier: Development Status :: 4 - Beta
Classifier: Intended Audience :: Developers
Classifier: License :: OSI Approved :: GNU Affero General Public License v3
Classifier: Topic :: Software Development :: Libraries :: Python Modules
Classifier: Topic :: Internet :: WWW/HTTP :: Site Management
Classifier: Topic :: Internet
License-File: LICENSE
Requires-Dist: requests
Requires-Dist: future
Requires-Dist: importlib-metadata ; python_version < "3.8"
